litestar_django/__init__.py
litestar_django/dto.py
litestar_django/plugin.py
litestar_django/types.py
litestar_django-0.2.2.dist-info/licenses/LICENSE
litestar_django-0.2.2.dist-info/METADATA
litestar_django-0.2.2.dist-info/WHEEL
litestar_django-0.2.2.dist-info/top_level.txt
litestar_django-0.2.2.dist-info/RECORD
