Metadata-Version: 2.4
Name: litestar-django
Version: 0.2.2
Summary: Django model support for Litestar
Author-email: Janek Nouvertné <janek@litestar.dev>
Maintainer-email: Litestar Developers <hello@litestar.dev>
License: MIT
Requires-Python: >=3.9
License-File: LICENSE
Requires-Dist: django>=4.2.20
Requires-Dist: litestar>=2.16.0
Dynamic: license-file
